fifo.v
module fifo (
    input [7:0] data_in,
    input [4:0]ptr_in,
    input [4:0]ptr_out,
    input en_read,en_write,reset,clk,
    output reg [7:0] data_out
);
reg [7:0] register [15:0];
integer i;
always @(posedge clk) 
begin
    if (reset)
    begin
        for(i =0;i<16;i=i+1)
        begin
            register [i]= 8'd0; 
        end 
        data_out <=8'b0;
    end 
    else
    begin
        // case ({en_write,en_read})
        // 2'b01: register[ptr_in]<=data_in;
        // 2'b10: data_out <= register[ptr_out];
        // endcase 
        if  (en_read)
        begin
           register[ptr_in]<=data_in;
        end
        if  (en_write)
        begin
            data_out <= register[ptr_out];
        end 
        else 
        begin
            data_out<=0;
        end
    end 
end
endmodule

fifo_tb.v
`include "fifo.v"

module fifo_tb;

  // Inputs
  reg [7:0] data_in;
  reg [4:0] ptr_in, ptr_out;
  reg en_read, reset, clk, en_write;

  // Outputs
  wire [7:0] data_out;

  // Instantiate the FIFO module
  fifo fifo1 (
    .data_in(data_in),
    .ptr_in(ptr_in),
    .ptr_out(ptr_out),
    .en_read(en_read),
    .en_write(en_write),
    .reset(reset),
    .clk(clk),
    .data_out(data_out)
  );

  // Clock generation
  // reg clk_gen;
  always #5 clk = ~clk;

  // Initial block for test scenarios
  initial begin
    // Dump VCD file
    $dumpfile("fifo_tb.vcd");
    $dumpvars(0, fifo_tb);

    // Initialize inputs
    clk = 0;
    reset = 1;
    en_read = 0;
    en_write = 0;
    data_in = 8'h00;
    ptr_in = 5'b00000; // Initial value for ptr_in
    ptr_out = 5'b00000; // Initial value for ptr_out

    // Apply reset
    #10 reset = 0;

    // Test scenario 1: Write data, then read it
    #20 en_write = 1; data_in = 8'h0A; ptr_in = ptr_in + 1; // Write data
    #10 en_write = 0;                  // Stop writing
    #20 en_read = 1; ptr_out = ptr_out + 1; // Start reading
    #10 en_read = 0;                   // Stop reading

    // Test scenario 2: Write multiple data, then read them
    #20 en_write = 1; data_in = 8'h0A; ptr_in = ptr_in + 1; // Write data
    #10 en_write = 1; data_in = 8'h1B; ptr_in = ptr_in + 1; // Write more data
    #10 en_write = 0;                  // Stop writing
    #20 en_read = 1; ptr_out = ptr_out + 1; // Start reading
    #10 en_read = 0;                   // Stop reading

    // Test scenario 3: Underflow condition (read without writing)
    #20 en_read = 1; ptr_out = ptr_out + 1; // Start reading
    #10 en_read = 0;                   // Stop reading

    // Test scenario 4: Overflow condition (write without reading)
    #20 en_write = 1; data_in = 8'h0A; ptr_in = ptr_in + 1; // Write data
    #10 en_write = 1; data_in = 8'h1B; ptr_in = ptr_in + 1; // Write more data
    #10 en_write = 1; data_in = 8'h2C; ptr_in = ptr_in + 1; // Write more data
    #10 en_write = 0;                  // Stop writing

    // Test scenario 5: Full cycle with more data
    #20 en_write = 1; data_in = 8'h0A; ptr_in = ptr_in + 1; // Write data
    #10 en_write = 1; data_in = 8'h1B; ptr_in = ptr_in + 1; // Write more data
    #10 en_write = 1; data_in = 8'h2C; ptr_in = ptr_in + 1; // Write more data
    #20 en_read = 1; ptr_out = ptr_out + 1; // Start reading
    #10 en_read = 0;                   // Stop reading

    // Test scenario 6: Alternating Write and Read
    #20 en_write = 1; data_in = 8'h0A; ptr_in = ptr_in + 1; // Write data
    #10 en_write = 0;                  // Stop writing
    #20 en_read = 1; ptr_out = ptr_out + 1; // Start reading
    #10 en_read = 0;                   // Stop reading
    #20 en_write = 1; data_in = 8'h1B; ptr_in = ptr_in + 1; // Write more data
    #10 en_write = 0;                  // Stop writing
    #20 en_read = 1; ptr_out = ptr_out + 1; // Start reading
    #10 en_read = 0;                   // Stop reading

    // End simulation
    #10 $finish;
  end

  // Always block for clock generation

endmodule

fifo_tb.vcd
$date
	Tue Jan 16 12:10:44 2024
$end
$version
	Icarus Verilog
$end
$timescale
	1s
$end
$scope module fifo_tb $end
$var wire 8 ! data_out [7:0] $end
$var reg 1 " clk $end
$var reg 8 # data_in [7:0] $end
$var reg 1 $ en_read $end
$var reg 1 % en_write $end
$var reg 5 & ptr_in [4:0] $end
$var reg 5 ' ptr_out [4:0] $end
$var reg 1 ( reset $end
$scope module fifo1 $end
$var wire 1 " clk $end
$var wire 8 ) data_in [7:0] $end
$var wire 1 $ en_read $end
$var wire 1 % en_write $end
$var wire 5 * ptr_in [4:0] $end
$var wire 5 + ptr_out [4:0] $end
$var wire 1 ( reset $end
$var reg 8 , data_out [7:0] $end
$var integer 32 - i [31:0] $end
$upscope $end
$upscope $end
$enddefinitions $end
$comment Show the parameter values. $end
$dumpall
$end
#0
$dumpvars
bx -
bx ,
b0 +
b0 *
b0 )
1(
b0 '
b0 &
0%
0$
b0 #
0"
bx !
$end
#5
b0 !
b0 ,
b10000 -
1"
#10
0"
0(
#15
1"
#20
0"
#25
1"
#30
0"
b1 &
b1 *
b1010 #
b1010 )
1%
#35
1"
#40
0"
0%
#45
1"
#50
0"
#55
1"
#60
0"
b1 '
b1 +
1$
#65
1"
#70
0"
0$
#75
1"
#80
0"
#85
1"
#90
0"
b10 &
b10 *
1%
#95
b1010 !
b1010 ,
1"
#100
0"
b11 &
b11 *
b11011 #
b11011 )
#105
1"
#110
0"
0%
#115
b0 !
b0 ,
1"
#120
0"
#125
1"
#130
0"
b10 '
b10 +
1$
#135
1"
#140
0"
0$
#145
1"
#150
0"
#155
1"
#160
0"
b11 '
b11 +
1$
#165
1"
#170
0"
0$
#175
1"
#180
0"
#185
1"
#190
0"
b100 &
b100 *
b1010 #
b1010 )
1%
#195
b11011 !
b11011 ,
1"
#200
0"
b101 &
b101 *
b11011 #
b11011 )
#205
1"
#210
0"
b110 &
b110 *
b101100 #
b101100 )
#215
1"
#220
0"
0%
#225
b0 !
b0 ,
1"
#230
0"
#235
1"
#240
0"
b111 &
b111 *
b1010 #
b1010 )
1%
#245
b11011 !
b11011 ,
1"
#250
0"
b1000 &
b1000 *
b11011 #
b11011 )
#255
1"
#260
0"
b1001 &
b1001 *
b101100 #
b101100 )
#265
1"
#270
0"
#275
1"
#280
0"
b100 '
b100 +
1$
#285
b0 !
b0 ,
1"
#290
0"
0$
#295
1"
#300
0"
#305
1"
#310
0"
b1010 &
b1010 *
b1010 #
b1010 )
#315
1"
#320
0"
0%
#325
1"
#330
0"
#335
1"
#340
0"
b101 '
b101 +
1$
#345
1"
#350
0"
0$
#355
1"
#360
0"
#365
1"
#370
0"
b1011 &
b1011 *
b11011 #
b11011 )
1%
#375
1"
#380
0"
0%
#385
1"
#390
0"
#395
1"
#400
0"
b110 '
b110 +
1$
#405
1"
#410
0"
0$
