fifo_test_2.v
module fifo_2 (
    input [7:0] data_in,
    input en_read, en_write, reset, clk,
    output reg overflow, underflow,
    output reg [7:0] data_out
);

reg [7:0] register [0:15];
reg [3:0] ptr_wr;
integer i;

always @(posedge clk ,posedge reset) 
begin
    if (reset)
    begin
        for (i = 0; i < 16; i = i + 1)
        begin
            register[i] = 8'd0; 
        end 
        data_out <= 8'b0;
        ptr_wr <= 4'd15;
        overflow <= 0;
        underflow <= 0;
    end 
    else
    begin
        if (ptr_wr != 4'b0)
            begin
                overflow <= 1'b0;
            end
            else
                overflow <= 1'b1;
        if (ptr_wr==15)
            begin
                underflow<=1;
            end
        else
            begin
                underflow<=0;
            end
        if (en_write)
        begin
            register[ptr_wr] <= data_in;
            if (!overflow)
            begin
                ptr_wr <= ptr_wr - 1;
            end
        end
        if (en_read)
        begin
            if (!underflow)
            begin
                data_out <= register[15];
                for (i = 15; i > ptr_wr; i = i - 1)
                begin
                    register[i] <= register[i - 1];
                end
                ptr_wr <= ptr_wr + 1;
            end
        end
        else 
        begin
            data_out <= 8'b0;
        end
    end 
end

endmodule

fif_test_2_tb.v
`timescale 1ns / 1ps
`include "fifo_test_2.v"

module fifo_2_tb;

  // Inputs
  reg [7:0] data_in;
  reg en_read, reset, clk, en_write;
  integer i = 0;
  wire underflow, overflow;

  // Outputs
  wire [7:0] data_out;

  // Instantiate the FIFO module
  fifo_2 fifo_inst (
    .data_in(data_in),
    .en_read(en_read),
    .reset(reset),
    .clk(clk),
    .en_write(en_write),
    .data_out(data_out),
    .underflow(underflow),
    .overflow(overflow)
  );

  // Clock generation
  always #5 clk = ~clk;

  // Initial block for test scenarios
  initial begin
    $dumpfile("fifo_2_tb.vcd");
    $dumpvars(0, fifo_2_tb);
  end

  // Rest of the initial block
  initial begin
    // Dump VCD file
    // Initialize inputs
    clk = 1;
    reset = 1;
    en_read = 0;
    en_write = 0;
    data_in = 8'h00;
    #5
    reset = 0;
    en_read = 0;
    en_write = 1;

    // Use a for loop to generate random values
    for (i = 0; i < 16; i = i + 1) begin
      data_in = $random % 256; // 256 is 2^8
      $display("Random 8-bit Number[%0d]: %h", i, data_in);
      #10;
    end

    en_read = 1;
    en_write = 0;
    #160 $finish;
  end

endmodule

fifo_2_tb.vcd
$date
	Sun Jan 21 12:54:31 2024
$end
$version
	Icarus Verilog
$end
$timescale
	1ps
$end
$scope module fifo_2_tb $end
$var wire 1 ! underflow $end
$var wire 1 " overflow $end
$var wire 8 # data_out [7:0] $end
$var reg 1 $ clk $end
$var reg 8 % data_in [7:0] $end
$var reg 1 & en_read $end
$var reg 1 ' en_write $end
$var reg 1 ( reset $end
$var integer 32 ) i [31:0] $end
$scope module fifo_inst $end
$var wire 1 $ clk $end
$var wire 8 * data_in [7:0] $end
$var wire 1 & en_read $end
$var wire 1 ' en_write $end
$var wire 1 ( reset $end
$var reg 8 + data_out [7:0] $end
$var reg 1 " overflow $end
$var reg 4 , ptr_wr [3:0] $end
$var reg 1 ! underflow $end
$var integer 32 - i [31:0] $end
$upscope $end
$upscope $end
$enddefinitions $end
$comment Show the parameter values. $end
$dumpall
$end
#0
$dumpvars
b10000 -
b1111 ,
b0 +
b0 *
b0 )
1(
0'
0&
b0 %
1$
b0 #
0"
0!
$end
#5000
b100100 %
b100100 *
1'
0(
0$
#10000
b1110 ,
1!
1$
#15000
0$
b10000001 %
b10000001 *
b1 )
#20000
b1101 ,
0!
1$
#25000
0$
b1001 %
b1001 *
b10 )
#30000
b1100 ,
1$
#35000
0$
b1100011 %
b1100011 *
b11 )
#40000
b1011 ,
1$
#45000
0$
b1101 %
b1101 *
b100 )
#50000
b1010 ,
1$
#55000
0$
b10001101 %
b10001101 *
b101 )
#60000
b1001 ,
1$
#65000
0$
b1100101 %
b1100101 *
b110 )
#70000
b1000 ,
1$
#75000
0$
b10010 %
b10010 *
b111 )
#80000
b111 ,
1$
#85000
0$
b1 %
b1 *
b1000 )
#90000
b110 ,
1$
#95000
0$
b1101 %
b1101 *
b1001 )
#100000
b101 ,
1$
#105000
0$
b1110110 %
b1110110 *
b1010 )
#110000
b100 ,
1$
#115000
0$
b111101 %
b111101 *
b1011 )
#120000
b11 ,
1$
#125000
0$
b11101101 %
b11101101 *
b1100 )
#130000
b10 ,
1$
#135000
0$
b10001100 %
b10001100 *
b1101 )
#140000
b1 ,
1$
#145000
0$
b11111001 %
b11111001 *
b1110 )
#150000
b0 ,
1$
#155000
0$
b11000110 %
b11000110 *
b1111 )
#160000
b1111 ,
1"
1$
#165000
0$
0'
1&
b10000 )
#170000
b0 ,
b100100 #
b100100 +
1!
0"
b1111 -
1$
#175000
0$
#180000
0!
1"
1$
#185000
0$
#190000
b1 ,
b0 -
1$
#195000
0$
#200000
b10 ,
b10000001 #
b10000001 +
0"
b1 -
1$
#205000
0$
#210000
b11 ,
b1001 #
b1001 +
b10 -
1$
#215000
0$
#220000
b100 ,
b1100011 #
b1100011 +
b11 -
1$
#225000
0$
#230000
b101 ,
b1101 #
b1101 +
b100 -
1$
#235000
0$
#240000
b110 ,
b10001101 #
b10001101 +
b101 -
1$
#245000
0$
#250000
b111 ,
b1100101 #
b1100101 +
b110 -
1$
#255000
0$
#260000
b1000 ,
b10010 #
b10010 +
b111 -
1$
#265000
0$
#270000
b1001 ,
b1 #
b1 +
b1000 -
1$
#275000
0$
#280000
b1010 ,
b1101 #
b1101 +
b1001 -
1$
#285000
0$
#290000
b1011 ,
b1110110 #
b1110110 +
b1010 -
1$
#295000
0$
#300000
b1100 ,
b111101 #
b111101 +
b1011 -
1$
#305000
0$
#310000
b1101 ,
b11101101 #
b11101101 +
b1100 -
1$
#315000
0$
#320000
b1110 ,
b10001100 #
b10001100 +
b1101 -
1$
