fifo.v
module fifo (
    input [7:0] data_in,
    input [4:0]ptr_in,
    input [4:0]ptr_out,
    input en_read,en_write,reset,clk,
    output reg [7:0] data_out
);
reg [7:0] register [15:0];
integer i;
always @(posedge clk) 
begin
    if (reset)
    begin
        for(i =0;i<16;i=i+1)
        begin
            register [i]= 8'd0; 
        end 
        data_out <=8'b0;
    end 
    else
    begin
        // case ({en_write,en_read})
        // 2'b01: register[ptr_in]<=data_in;
        // 2'b10: data_out <= register[ptr_out];
        // endcase 
        if  (en_write)
        begin
           register[ptr_in]<=data_in;
        end
        if  (en_read)
        begin
            data_out <= register[ptr_out];
        end 
        else 
        begin
            data_out<=0;
        end
    end 
end
endmodule

fifo_output_control_unit.v
// TODO: add  data_out  in the top module  
module fifo_output_control (
    input  read_en, reset, clk,
    input [7:0]data_out,
    output reg read_en_o, 
    output reg underflow,
    output reg [4:0] ptr,
    output reg [7:0]data_out_f
);

    reg [4:0] count = 0;

    always @(posedge clk ) begin
        if (reset) begin
            count <= 5'b0;
            ptr <= 5'b0;
            underflow <= 1'b0;
            data_out_f <=0;
        end
        else begin
            if (read_en ) begin
                if  (data_out != 8'd0) begin
                    underflow <= 1'b0;
                    count <= count + 1;
                    ptr <= count;
                    read_en_o <= 1'b1;
                    data_out_f <=data_out;
                end
                else begin
                    underflow <= 1'b1;
                    read_en_o <= 1'b0;
                    data_out_f <=0;
                end
            end
            else begin
                read_en_o <= 1'b0;
            end
        end
    end
endmodule

fifo_input_control.v
module fifo_input_control (
    input write_en,reset,clk,
    output reg write_en_o,overflow,
    output reg [4:0] ptr
);
reg [4:0]count=0;
always @(clk) 
begin
    if (reset)
    begin
        count <= 5'b0;
        ptr <= 5'b0;
        overflow <= 1'b0;
    end    
    else 
    begin
        if(write_en)
        begin
            if (count!=5'b1111)
            begin
                write_en_o <=1;
                overflow<=  0;
                count <= count+1;
                ptr<=count;
            end
            else
            begin
                overflow <=1; 
                write_en_o <=0;
            end
        end
        else 
        begin
            write_en_o <= 1'b0;
        end
    end
end
endmodule

top.v
//TODO: add overflow and underflow to the output list
`include "fifo_output_control_unit.v"
`include "fifo_input_control.v"
`include "fifo.v"
module top (
    input clk,reset,read_en,write_en,
    input [7:0]data_in,
    output [7:0]data_out,
    output overflow,underflow
);
wire [4:0] ptr_of;
wire [4:0] ptr_uf;
wire [7:0]data_out_1;
// fifo input cotrol takes data from processor 1
fifo_input_control fifo_input_control1 (
    .write_en(write_en), .reset(reset), .clk(clk),
    .write_en_o(write_en_o), .overflow(overflow),
    .ptr(ptr_of)
);
// fifo output control gets data from the fifo to processor 2
fifo_output_control fifo_output_control2 (
    .read_en(read_en), .reset(reset), .clk(clk),
    .read_en_o(read_en_o), .underflow(underflow),
    .ptr(ptr_uf),
    .data_out(data_out_1),
    .data_out_f(data_out)
);
// main inititalizaton
fifo fifo_inst (
    .data_in(data_in),
    .ptr_in(ptr_of),
    .ptr_out(ptr_uf),
    .en_read(read_en_o),
    .en_write(write_en_o),
    .reset(reset),
    .clk(clk),
    .data_out(data_out_1)
);



endmodule

top_tb.v
`timescale 1ns/1ns
`include "top.v"
module tb_top;

  reg clk, reset, read_en, write_en;
  reg [7:0] data_in;
  wire [7:0] data_out;
  wire overflow,underflow;
  // Clock generation
  always begin
    #5 clk = ~clk;
  end

  // Instantiate the DUT
  top uut (
    .clk(clk),
    .reset(reset),
    .read_en(read_en),
    .write_en(write_en),
    .data_in(data_in),
    .data_out(data_out),
    .overflow(overflow),
    .underflow(underflow)
  );
initial
begin
    // Dump VCD file
    $dumpfile("tb_top.vcd");
    $dumpvars(0, tb_top);
end
  // Initialize signals
  initial begin
    clk = 1;
    reset = 1;
    read_en = 0;
    write_en = 0;
    data_in = 8'h00;


    // Apply reset
    #10 reset = 0;

    // Scenario 1: Write data, then read it
    #20 write_en = 1; data_in = 8'h0A; // Write data
    #10 write_en = 0;                  // Stop writing
    #20 read_en = 1;                   // Start reading
    #10 read_en = 0;                   // Stop reading

    // Scenario 2: Write multiple data, then read them
    #20 write_en = 1; data_in = 8'h0A; // Write data
    #10 write_en = 1; data_in = 8'h1B; // Write more data
    #10 write_en = 0;                  // Stop writing
    #20 read_en = 1;                   // Start reading
    #10 read_en = 0;                   // Stop reading

    // Scenario 3: Underflow condition (read without writing)
    #20 read_en = 1;                   // Start reading
    #10 read_en = 0;                   // Stop reading

    // Scenario 4: Overflow condition (write without reading)
    #20 write_en = 1; data_in = 8'h0A; // Write data
    #10 write_en = 1; data_in = 8'h1B; // Write more data
    #10 write_en = 1; data_in = 8'h2C; // Write more data
    #10 write_en = 0;                  // Stop writing

    // Scenario 5: Full cycle with more data
    #20 write_en = 1; data_in = 8'h0A; // Write data
    #10 write_en = 1; data_in = 8'h1B; // Write more data
    #10 write_en = 1; data_in = 8'h2C; // Write more data
    #20 read_en = 1;                   // Start reading
    #10 read_en = 0;                   // Stop reading

    // Scenario 6: Alternating Write and Read
    #20 write_en = 1; data_in = 8'h0A; // Write data
    #10 write_en = 0;                  // Stop writing
    #20 read_en = 1;                   // Start reading
    #10 read_en = 0;                   // Stop reading
    #20 write_en = 1; data_in = 8'h1B; // Write more data
    #10 write_en = 0;                  // Stop writing
    #20 read_en = 1;                   // Start reading
    #10 read_en = 0;                   // Stop reading


    // End simulation
    #10 $finish;
  end

endmodule

tb_top.vcd
$date
	Wed Jan 17 12:25:11 2024
$end
$version
	Icarus Verilog
$end
$timescale
	1ns
$end
$scope module tb_top $end
$var wire 1 ! underflow $end
$var wire 1 " overflow $end
$var wire 8 # data_out [7:0] $end
$var reg 1 $ clk $end
$var reg 8 % data_in [7:0] $end
$var reg 1 & read_en $end
$var reg 1 ' reset $end
$var reg 1 ( write_en $end
$scope module uut $end
$var wire 1 $ clk $end
$var wire 8 ) data_in [7:0] $end
$var wire 1 & read_en $end
$var wire 1 ' reset $end
$var wire 1 ( write_en $end
$var wire 1 * write_en_o $end
$var wire 1 ! underflow $end
$var wire 1 + read_en_o $end
$var wire 5 , ptr_uf [4:0] $end
$var wire 5 - ptr_of [4:0] $end
$var wire 1 " overflow $end
$var wire 8 . data_out_1 [7:0] $end
$var wire 8 / data_out [7:0] $end
$scope module fifo_input_control1 $end
$var wire 1 $ clk $end
$var wire 1 ' reset $end
$var wire 1 ( write_en $end
$var reg 5 0 count [4:0] $end
$var reg 1 " overflow $end
$var reg 5 1 ptr [4:0] $end
$var reg 1 * write_en_o $end
$upscope $end
$scope module fifo_inst $end
$var wire 1 $ clk $end
$var wire 8 2 data_in [7:0] $end
$var wire 1 * en_write $end
$var wire 5 3 ptr_in [4:0] $end
$var wire 1 ' reset $end
$var wire 5 4 ptr_out [4:0] $end
$var wire 1 + en_read $end
$var reg 8 5 data_out [7:0] $end
$var integer 32 6 i [31:0] $end
$upscope $end
$scope module fifo_output_control2 $end
$var wire 1 $ clk $end
$var wire 8 7 data_out [7:0] $end
$var wire 1 & read_en $end
$var wire 1 ' reset $end
$var reg 5 8 count [4:0] $end
$var reg 8 9 data_out_f [7:0] $end
$var reg 5 : ptr [4:0] $end
$var reg 1 + read_en_o $end
$var reg 1 ! underflow $end
$upscope $end
$upscope $end
$upscope $end
$enddefinitions $end
$comment Show the parameter values. $end
$dumpall
$end
#0
$dumpvars
b0 :
b0 9
b0 8
b0 7
b10000 6
b0 5
b0 4
b0 3
b0 2
b0 1
b0 0
b0 /
b0 .
b0 -
b0 ,
x+
x*
b0 )
0(
1'
0&
b0 %
1$
b0 #
0"
0!
$end
#5
0$
#10
0*
0+
1$
0'
#15
0$
#20
1$
#25
0$
#30
b1 0
1*
1$
b1010 %
b1010 )
b1010 2
1(
#35
b1 -
b1 1
b1 3
b10 0
0$
#40
0*
1$
0(
#45
0$
#50
1$
#55
0$
#60
1!
1$
1&
#65
0$
#70
1$
0&
#75
0$
#80
1$
#85
0$
#90
b10 -
b10 1
b10 3
b11 0
1*
1$
1(
#95
b11 -
b11 1
b11 3
b100 0
0$
#100
b100 -
b100 1
b100 3
b101 0
1$
b11011 %
b11011 )
b11011 2
#105
b101 -
b101 1
b101 3
b110 0
0$
#110
0*
1$
0(
#115
0$
#120
1$
#125
0$
#130
1$
1&
#135
0$
#140
1$
0&
#145
0$
#150
1$
#155
0$
#160
1$
1&
#165
0$
#170
1$
0&
#175
0$
#180
1$
#185
0$
#190
b110 -
b110 1
b110 3
b111 0
1*
1$
b1010 %
b1010 )
b1010 2
1(
#195
b111 -
b111 1
b111 3
b1000 0
0$
#200
b1000 -
b1000 1
b1000 3
b1001 0
1$
b11011 %
b11011 )
b11011 2
#205
b1001 -
b1001 1
b1001 3
b1010 0
0$
#210
b1010 -
b1010 1
b1010 3
b1011 0
1$
b101100 %
b101100 )
b101100 2
#215
b1011 -
b1011 1
b1011 3
b1100 0
0$
#220
0*
1$
0(
#225
0$
#230
1$
#235
0$
#240
b1100 -
b1100 1
b1100 3
b1101 0
1*
1$
b1010 %
b1010 )
b1010 2
1(
#245
b1101 -
b1101 1
b1101 3
b1110 0
0$
#250
b1110 -
b1110 1
b1110 3
b1111 0
1$
b11011 %
b11011 )
b11011 2
#255
0*
1"
0$
#260
1$
b101100 %
b101100 )
b101100 2
#265
0$
#270
1$
#275
0$
#280
1$
1&
#285
0$
#290
1$
0&
#295
0$
#300
1$
#305
0$
#310
1$
b1010 %
b1010 )
b1010 2
#315
0$
#320
1$
0(
#325
0$
#330
1$
#335
0$
#340
1$
1&
#345
0$
#350
1$
0&
#355
0$
#360
1$
#365
0$
#370
1$
b11011 %
b11011 )
b11011 2
1(
#375
0$
#380
1$
0(
#385
0$
#390
1$
#395
0$
#400
1$
1&
#405
0$
#410
1$
0&
